ppsim-1.0.2.dist-info/METADATA
ppsim-1.0.2.dist-info/WHEEL
ppsim-1.0.2.dist-info/licenses/LICENSE
ppsim.libs/libgcc_s-b5472b99.so.1
ppsim/__init__.py
ppsim/crn.py
ppsim/ppsim_rust/.gitignore
ppsim/ppsim_rust/__init__.py
ppsim/ppsim_rust/ppsim_rust.pyi
ppsim/ppsim_rust/ppsim_rust.pypy310-pp73-x86-linux-gnu.so
ppsim/py.typed
ppsim/simulation.py
ppsim/snapshot.py
ppsim-1.0.2.dist-info/RECORD
